ecoledirecte_py_client/__init__.py
ecoledirecte_py_client/client.py
ecoledirecte_py_client/exceptions.py
ecoledirecte_py_client/family.py
ecoledirecte_py_client/mfa.py
ecoledirecte_py_client/models.py
ecoledirecte_py_client/student.py
ecoledirecte_py_client/managers/base_manager.py
ecoledirecte_py_client/managers/grades_manager.py
ecoledirecte_py_client/managers/homework_manager.py
ecoledirecte_py_client/managers/messages_manager.py
ecoledirecte_py_client/managers/schedule_manager.py
ecoledirecte_py_client/models/__init__.py
ecoledirecte_py_client/models/auth.py
ecoledirecte_py_client/models/common.py
ecoledirecte_py_client/models/grades.py
ecoledirecte_py_client/models/homework.py
ecoledirecte_py_client/models/messages.py
ecoledirecte_py_client/models/schedule.py
ecoledirecte_py_client-0.2.1.dist-info/METADATA
ecoledirecte_py_client-0.2.1.dist-info/WHEEL
ecoledirecte_py_client-0.2.1.dist-info/licenses/LICENSE
ecoledirecte_py_client-0.2.1.dist-info/RECORD
