Metadata-Version: 2.4
Name: ecoledirecte-py-client
Version: 0.2.1
Summary: A comprehensive Python client for the EcoleDirecte API with MFA support.
Project-URL: Homepage, https://github.com/ngombert/ecoledirecte-py-client
Project-URL: Repository, https://github.com/ngombert/ecoledirecte-py-client
Project-URL: Issues, https://github.com/ngombert/ecoledirecte-py-client/issues
Author-email: Nicolas GOMBERT <gombert.n@gmail.com>
License: GPL-3.0-or-later
License-File: LICENSE
Keywords: api-client,ecoledirecte,education,france,mfa,student
Classifier: Development Status :: 3 - Alpha
Classifier: Intended Audience :: Developers
Classifier: Intended Audience :: Education
Classifier: License :: OSI Approved :: GNU General Public License v3 or later (GPLv3+)
Classifier: Operating System :: OS Independent
Classifier: Programming Language :: Python :: 3
Classifier: Programming Language :: Python :: 3.9
Classifier: Programming Language :: Python :: 3.10
Classifier: Programming Language :: Python :: 3.11
Classifier: Programming Language :: Python :: 3.12
Classifier: Programming Language :: Python :: 3.13
Classifier: Topic :: Education
Classifier: Topic :: Internet :: WWW/HTTP
Classifier: Topic :: Software Development :: Libraries :: Python Modules
Requires-Python: >=3.9
Requires-Dist: httpx>=0.28.1
Requires-Dist: pydantic>=2.12.5
